panovel/__init__.py
panovel/book_conversion.py
panovel/console_script.py
panovel/filter.py
panovel/main.py
panovel/metadata.py
panovel/utils.py
panovel/filter/alignment.py
panovel/filter/backmatter.py
panovel/filter/copyrights.py
panovel/filter/custom_styles.py
panovel/filter/dedication.py
panovel/filter/epigraph.py
panovel/filter/epub_remove_fm_head.py
panovel/filter/frontmatter.py
panovel/filter/heading_image.py
panovel/filter/new_page.py
panovel/filter/new_scene.py
panovel/filter/noindent.py
panovel/filter/poem.py
panovel/filter/quote.py
panovel/filter/remove_comments.py
panovel/filter/remove_images.py
panovel/styles/_navigation.scss
panovel/styles/epub_stylesheet.scss
panovel/styles/html_stylesheet.scss
panovel/styles/pdf_styles.tex
panovel/templates/gitignore.template
panovel/templates/html.template
panovel/templates/pdf.template
panovel-0.51.dist-info/METADATA
panovel-0.51.dist-info/RECORD
panovel-0.51.dist-info/WHEEL
panovel-0.51.dist-info/entry_points.txt
panovel-0.51.dist-info/top_level.txt
