Metadata-Version: 2.1
Name: panovel
Version: 0.51
Summary: A script to make a novel out of markdown files with the help of pandoc
Home-page: https://github.com/dickloraine/panovel
Author: dickloraine
Author-email: dickloraine@gmx.net
License: MIT
Keywords: pandoc novel writing text conversion
Platform: UNKNOWN
Classifier: Development Status :: 4 - Beta
Classifier: Programming Language :: Python :: 3.6
Classifier: Operating System :: OS Independent
Classifier: Natural Language :: English
Classifier: Intended Audience :: End Users/Desktop
Classifier: Topic :: Text Processing
Classifier: License :: OSI Approved :: MIT License
Requires-Python: >=3.6
Requires-Dist: pyYaml
Requires-Dist: panflute
Requires-Dist: pyscss
